README.md
setup.cfg
setup.py
smt_design_space_ext/__init__.py
smt_design_space_ext/adsg_ds_imp.py
smt_design_space_ext/cs_ds_imp.py
smt_design_space_ext/design_space.py
smt_design_space_ext/version.py
smt_design_space_ext.egg-info/PKG-INFO
smt_design_space_ext.egg-info/SOURCES.txt
smt_design_space_ext.egg-info/dependency_links.txt
smt_design_space_ext.egg-info/requires.txt
smt_design_space_ext.egg-info/top_level.txt