Metadata-Version: 2.4
Name: smt_design_space_ext
Version: 0.3.1
Summary: SMT design space extension for hierarchical variables handling
Home-page: https://github.com/SMTorg/smt-design-space
Download-URL: https://github.com/SMTorg/smt-design-space/releases
Author: Paul Saves et al.
Author-email: paul.saves@onera.fr
Maintainer: Paul Saves
Maintainer-email: paul.saves@onera.fr
License: BSD-3
Keywords: SMT, DesignSpace, Graph
Requires-Python: >=3.9
Requires-Dist: numpy
Requires-Dist: smt>=2.8
Requires-Dist: ConfigSpace==0.6.1
Requires-Dist: adsg-core==1.1.1
Dynamic: author
Dynamic: author-email
Dynamic: download-url
Dynamic: home-page
Dynamic: keywords
Dynamic: license
Dynamic: maintainer
Dynamic: maintainer-email
Dynamic: requires-dist
Dynamic: requires-python
Dynamic: summary
